<?xml version="1.0"?>
<!-- <!DOCTYPE Tags SYSTEM "matroskatags.dtd"> -->
<Tags>
  <Tag>
    <Targets>
      <TargetTypeValue>50</TargetTypeValue>
      <TrackUID>10626001262705037237</TrackUID>
      <TargetType>MOVIE</TargetType>
    </Targets>
    <Simple>
      <Name>BPS</Name>
      <TagLanguage>eng</TagLanguage>
      <DefaultLanguage>1</DefaultLanguage>
      <String>2552353</String>
    </Simple>
    <Simple>
      <Name>DURATION</Name>
      <TagLanguage>eng</TagLanguage>
      <DefaultLanguage>1</DefaultLanguage>
      <String>00:24:47.862000000</String>
    </Simple>
    <Simple>
      <Name>NUMBER_OF_FRAMES</Name>
      <TagLanguage>eng</TagLanguage>
      <DefaultLanguage>1</DefaultLanguage>
      <String>35673</String>
    </Simple>
    <Simple>
      <Name>NUMBER_OF_BYTES</Name>
      <TagLanguage>eng</TagLanguage>
      <DefaultLanguage>1</DefaultLanguage>
      <String>474693684</String>
    </Simple>
    <Simple>
      <Name>_STATISTICS_WRITING_APP</Name>
      <TagLanguage>eng</TagLanguage>
      <DefaultLanguage>1</DefaultLanguage>
      <String>mkvmerge v16.0.0 ('Protest') 32-bit</String>
    </Simple>
    <Simple>
      <Name>_STATISTICS_WRITING_DATE_UTC</Name>
      <TagLanguage>eng</TagLanguage>
      <DefaultLanguage>1</DefaultLanguage>
      <String>2018-03-04 11:43:23</String>
    </Simple>
    <Simple>
      <Name>_STATISTICS_TAGS</Name>
      <TagLanguage>eng</TagLanguage>
      <DefaultLanguage>1</DefaultLanguage>
      <String>BPS DURATION NUMBER_OF_FRAMES NUMBER_OF_BYTES</String>
    </Simple>
  </Tag>
  <Tag>
    <Targets>
      <TargetTypeValue>50</TargetTypeValue>
      <TrackUID>9313401092684855991</TrackUID>
      <TargetType>MOVIE</TargetType>
    </Targets>
    <Simple>
      <Name>BPS</Name>
      <TagLanguage>eng</TagLanguage>
      <DefaultLanguage>1</DefaultLanguage>
      <String>128000</String>
    </Simple>
    <Simple>
      <Name>DURATION</Name>
      <TagLanguage>eng</TagLanguage>
      <DefaultLanguage>1</DefaultLanguage>
      <String>00:24:47.904000000</String>
    </Simple>
    <Simple>
      <Name>NUMBER_OF_FRAMES</Name>
      <TagLanguage>eng</TagLanguage>
      <DefaultLanguage>1</DefaultLanguage>
      <String>46497</String>
    </Simple>
    <Simple>
      <Name>NUMBER_OF_BYTES</Name>
      <TagLanguage>eng</TagLanguage>
      <DefaultLanguage>1</DefaultLanguage>
      <String>23806464</String>
    </Simple>
    <Simple>
      <Name>_STATISTICS_WRITING_APP</Name>
      <TagLanguage>eng</TagLanguage>
      <DefaultLanguage>1</DefaultLanguage>
      <String>mkvmerge v16.0.0 ('Protest') 32-bit</String>
    </Simple>
    <Simple>
      <Name>_STATISTICS_WRITING_DATE_UTC</Name>
      <TagLanguage>eng</TagLanguage>
      <DefaultLanguage>1</DefaultLanguage>
      <String>2018-03-04 11:43:23</String>
    </Simple>
    <Simple>
      <Name>_STATISTICS_TAGS</Name>
      <TagLanguage>eng</TagLanguage>
      <DefaultLanguage>1</DefaultLanguage>
      <String>BPS DURATION NUMBER_OF_FRAMES NUMBER_OF_BYTES</String>
    </Simple>
  </Tag>
  <Tag>
    <Targets>
      <TargetTypeValue>50</TargetTypeValue>
      <TrackUID>12223994311453075126</TrackUID>
      <TargetType>MOVIE</TargetType>
    </Targets>
    <Simple>
      <Name>BPS</Name>
      <TagLanguage>eng</TagLanguage>
      <DefaultLanguage>1</DefaultLanguage>
      <String>128000</String>
    </Simple>
    <Simple>
      <Name>DURATION</Name>
      <TagLanguage>eng</TagLanguage>
      <DefaultLanguage>1</DefaultLanguage>
      <String>00:24:47.904000000</String>
    </Simple>
    <Simple>
      <Name>NUMBER_OF_FRAMES</Name>
      <TagLanguage>eng</TagLanguage>
      <DefaultLanguage>1</DefaultLanguage>
      <String>46497</String>
    </Simple>
    <Simple>
      <Name>NUMBER_OF_BYTES</Name>
      <TagLanguage>eng</TagLanguage>
      <DefaultLanguage>1</DefaultLanguage>
      <String>23806464</String>
    </Simple>
    <Simple>
      <Name>_STATISTICS_WRITING_APP</Name>
      <TagLanguage>eng</TagLanguage>
      <DefaultLanguage>1</DefaultLanguage>
      <String>mkvmerge v16.0.0 ('Protest') 32-bit</String>
    </Simple>
    <Simple>
      <Name>_STATISTICS_WRITING_DATE_UTC</Name>
      <TagLanguage>eng</TagLanguage>
      <DefaultLanguage>1</DefaultLanguage>
      <String>2018-03-04 11:43:23</String>
    </Simple>
    <Simple>
      <Name>_STATISTICS_TAGS</Name>
      <TagLanguage>eng</TagLanguage>
      <DefaultLanguage>1</DefaultLanguage>
      <String>BPS DURATION NUMBER_OF_FRAMES NUMBER_OF_BYTES</String>
    </Simple>
  </Tag>
  <Tag>
    <Targets>
      <TargetTypeValue>50</TargetTypeValue>
      <TrackUID>9711925823000606143</TrackUID>
      <TargetType>MOVIE</TargetType>
    </Targets>
    <Simple>
      <Name>BPS</Name>
      <TagLanguage>eng</TagLanguage>
      <DefaultLanguage>1</DefaultLanguage>
      <String>128000</String>
    </Simple>
    <Simple>
      <Name>DURATION</Name>
      <TagLanguage>eng</TagLanguage>
      <DefaultLanguage>1</DefaultLanguage>
      <String>00:24:47.904000000</String>
    </Simple>
    <Simple>
      <Name>NUMBER_OF_FRAMES</Name>
      <TagLanguage>eng</TagLanguage>
      <DefaultLanguage>1</DefaultLanguage>
      <String>46497</String>
    </Simple>
    <Simple>
      <Name>NUMBER_OF_BYTES</Name>
      <TagLanguage>eng</TagLanguage>
      <DefaultLanguage>1</DefaultLanguage>
      <String>23806464</String>
    </Simple>
    <Simple>
      <Name>_STATISTICS_WRITING_APP</Name>
      <TagLanguage>eng</TagLanguage>
      <DefaultLanguage>1</DefaultLanguage>
      <String>mkvmerge v16.0.0 ('Protest') 32-bit</String>
    </Simple>
    <Simple>
      <Name>_STATISTICS_WRITING_DATE_UTC</Name>
      <TagLanguage>eng</TagLanguage>
      <DefaultLanguage>1</DefaultLanguage>
      <String>2018-03-04 11:43:23</String>
    </Simple>
    <Simple>
      <Name>_STATISTICS_TAGS</Name>
      <TagLanguage>eng</TagLanguage>
      <DefaultLanguage>1</DefaultLanguage>
      <String>BPS DURATION NUMBER_OF_FRAMES NUMBER_OF_BYTES</String>
    </Simple>
  </Tag>
  <Tag>
    <Targets>
      <TargetTypeValue>50</TargetTypeValue>
      <TrackUID>2036474150268367037</TrackUID>
      <TargetType>MOVIE</TargetType>
    </Targets>
    <Simple>
      <Name>BPS</Name>
      <TagLanguage>eng</TagLanguage>
      <DefaultLanguage>1</DefaultLanguage>
      <String>128000</String>
    </Simple>
    <Simple>
      <Name>DURATION</Name>
      <TagLanguage>eng</TagLanguage>
      <DefaultLanguage>1</DefaultLanguage>
      <String>00:24:47.904000000</String>
    </Simple>
    <Simple>
      <Name>NUMBER_OF_FRAMES</Name>
      <TagLanguage>eng</TagLanguage>
      <DefaultLanguage>1</DefaultLanguage>
      <String>46497</String>
    </Simple>
    <Simple>
      <Name>NUMBER_OF_BYTES</Name>
      <TagLanguage>eng</TagLanguage>
      <DefaultLanguage>1</DefaultLanguage>
      <String>23806464</String>
    </Simple>
    <Simple>
      <Name>_STATISTICS_WRITING_APP</Name>
      <TagLanguage>eng</TagLanguage>
      <DefaultLanguage>1</DefaultLanguage>
      <String>mkvmerge v16.0.0 ('Protest') 32-bit</String>
    </Simple>
    <Simple>
      <Name>_STATISTICS_WRITING_DATE_UTC</Name>
      <TagLanguage>eng</TagLanguage>
      <DefaultLanguage>1</DefaultLanguage>
      <String>2018-03-04 11:43:23</String>
    </Simple>
    <Simple>
      <Name>_STATISTICS_TAGS</Name>
      <TagLanguage>eng</TagLanguage>
      <DefaultLanguage>1</DefaultLanguage>
      <String>BPS DURATION NUMBER_OF_FRAMES NUMBER_OF_BYTES</String>
    </Simple>
  </Tag>
  <Tag>
    <Targets>
      <TargetTypeValue>50</TargetTypeValue>
      <TrackUID>9406251859669194906</TrackUID>
      <TargetType>MOVIE</TargetType>
    </Targets>
    <Simple>
      <Name>BPS</Name>
      <TagLanguage>eng</TagLanguage>
      <DefaultLanguage>1</DefaultLanguage>
      <String>128000</String>
    </Simple>
    <Simple>
      <Name>DURATION</Name>
      <TagLanguage>eng</TagLanguage>
      <DefaultLanguage>1</DefaultLanguage>
      <String>00:24:47.904000000</String>
    </Simple>
    <Simple>
      <Name>NUMBER_OF_FRAMES</Name>
      <TagLanguage>eng</TagLanguage>
      <DefaultLanguage>1</DefaultLanguage>
      <String>46497</String>
    </Simple>
    <Simple>
      <Name>NUMBER_OF_BYTES</Name>
      <TagLanguage>eng</TagLanguage>
      <DefaultLanguage>1</DefaultLanguage>
      <String>23806464</String>
    </Simple>
    <Simple>
      <Name>_STATISTICS_WRITING_APP</Name>
      <TagLanguage>eng</TagLanguage>
      <DefaultLanguage>1</DefaultLanguage>
      <String>mkvmerge v16.0.0 ('Protest') 32-bit</String>
    </Simple>
    <Simple>
      <Name>_STATISTICS_WRITING_DATE_UTC</Name>
      <TagLanguage>eng</TagLanguage>
      <DefaultLanguage>1</DefaultLanguage>
      <String>2018-03-04 11:43:23</String>
    </Simple>
    <Simple>
      <Name>_STATISTICS_TAGS</Name>
      <TagLanguage>eng</TagLanguage>
      <DefaultLanguage>1</DefaultLanguage>
      <String>BPS DURATION NUMBER_OF_FRAMES NUMBER_OF_BYTES</String>
    </Simple>
  </Tag>
  <Tag>
    <Targets>
      <TargetTypeValue>50</TargetTypeValue>
      <TrackUID>11624139354141142964</TrackUID>
      <TargetType>MOVIE</TargetType>
    </Targets>
    <Simple>
      <Name>BPS</Name>
      <TagLanguage>eng</TagLanguage>
      <DefaultLanguage>1</DefaultLanguage>
      <String>128000</String>
    </Simple>
    <Simple>
      <Name>DURATION</Name>
      <TagLanguage>eng</TagLanguage>
      <DefaultLanguage>1</DefaultLanguage>
      <String>00:24:47.904000000</String>
    </Simple>
    <Simple>
      <Name>NUMBER_OF_FRAMES</Name>
      <TagLanguage>eng</TagLanguage>
      <DefaultLanguage>1</DefaultLanguage>
      <String>46497</String>
    </Simple>
    <Simple>
      <Name>NUMBER_OF_BYTES</Name>
      <TagLanguage>eng</TagLanguage>
      <DefaultLanguage>1</DefaultLanguage>
      <String>23806464</String>
    </Simple>
    <Simple>
      <Name>_STATISTICS_WRITING_APP</Name>
      <TagLanguage>eng</TagLanguage>
      <DefaultLanguage>1</DefaultLanguage>
      <String>mkvmerge v16.0.0 ('Protest') 32-bit</String>
    </Simple>
    <Simple>
      <Name>_STATISTICS_WRITING_DATE_UTC</Name>
      <TagLanguage>eng</TagLanguage>
      <DefaultLanguage>1</DefaultLanguage>
      <String>2018-03-04 11:43:23</String>
    </Simple>
    <Simple>
      <Name>_STATISTICS_TAGS</Name>
      <TagLanguage>eng</TagLanguage>
      <DefaultLanguage>1</DefaultLanguage>
      <String>BPS DURATION NUMBER_OF_FRAMES NUMBER_OF_BYTES</String>
    </Simple>
  </Tag>
  <Tag>
    <Targets>
      <TargetTypeValue>50</TargetTypeValue>
      <TrackUID>13066278091498471822</TrackUID>
      <TargetType>MOVIE</TargetType>
    </Targets>
    <Simple>
      <Name>BPS</Name>
      <TagLanguage>eng</TagLanguage>
      <DefaultLanguage>1</DefaultLanguage>
      <String>128000</String>
    </Simple>
    <Simple>
      <Name>DURATION</Name>
      <TagLanguage>eng</TagLanguage>
      <DefaultLanguage>1</DefaultLanguage>
      <String>00:24:47.904000000</String>
    </Simple>
    <Simple>
      <Name>NUMBER_OF_FRAMES</Name>
      <TagLanguage>eng</TagLanguage>
      <DefaultLanguage>1</DefaultLanguage>
      <String>46497</String>
    </Simple>
    <Simple>
      <Name>NUMBER_OF_BYTES</Name>
      <TagLanguage>eng</TagLanguage>
      <DefaultLanguage>1</DefaultLanguage>
      <String>23806464</String>
    </Simple>
    <Simple>
      <Name>_STATISTICS_WRITING_APP</Name>
      <TagLanguage>eng</TagLanguage>
      <DefaultLanguage>1</DefaultLanguage>
      <String>mkvmerge v16.0.0 ('Protest') 32-bit</String>
    </Simple>
    <Simple>
      <Name>_STATISTICS_WRITING_DATE_UTC</Name>
      <TagLanguage>eng</TagLanguage>
      <DefaultLanguage>1</DefaultLanguage>
      <String>2018-03-04 11:43:23</String>
    </Simple>
    <Simple>
      <Name>_STATISTICS_TAGS</Name>
      <TagLanguage>eng</TagLanguage>
      <DefaultLanguage>1</DefaultLanguage>
      <String>BPS DURATION NUMBER_OF_FRAMES NUMBER_OF_BYTES</String>
    </Simple>
  </Tag>
  <Tag>
    <Targets>
      <TargetTypeValue>50</TargetTypeValue>
      <TrackUID>2830462255748378541</TrackUID>
      <TargetType>MOVIE</TargetType>
    </Targets>
    <Simple>
      <Name>BPS</Name>
      <TagLanguage>eng</TagLanguage>
      <DefaultLanguage>1</DefaultLanguage>
      <String>128000</String>
    </Simple>
    <Simple>
      <Name>DURATION</Name>
      <TagLanguage>eng</TagLanguage>
      <DefaultLanguage>1</DefaultLanguage>
      <String>00:24:47.904000000</String>
    </Simple>
    <Simple>
      <Name>NUMBER_OF_FRAMES</Name>
      <TagLanguage>eng</TagLanguage>
      <DefaultLanguage>1</DefaultLanguage>
      <String>46497</String>
    </Simple>
    <Simple>
      <Name>NUMBER_OF_BYTES</Name>
      <TagLanguage>eng</TagLanguage>
      <DefaultLanguage>1</DefaultLanguage>
      <String>23806464</String>
    </Simple>
    <Simple>
      <Name>_STATISTICS_WRITING_APP</Name>
      <TagLanguage>eng</TagLanguage>
      <DefaultLanguage>1</DefaultLanguage>
      <String>mkvmerge v16.0.0 ('Protest') 32-bit</String>
    </Simple>
    <Simple>
      <Name>_STATISTICS_WRITING_DATE_UTC</Name>
      <TagLanguage>eng</TagLanguage>
      <DefaultLanguage>1</DefaultLanguage>
      <String>2018-03-04 11:43:23</String>
    </Simple>
    <Simple>
      <Name>_STATISTICS_TAGS</Name>
      <TagLanguage>eng</TagLanguage>
      <DefaultLanguage>1</DefaultLanguage>
      <String>BPS DURATION NUMBER_OF_FRAMES NUMBER_OF_BYTES</String>
    </Simple>
  </Tag>
  <Tag>
    <Targets>
      <TargetTypeValue>50</TargetTypeValue>
      <TrackUID>17181837668381265560</TrackUID>
      <TargetType>MOVIE</TargetType>
    </Targets>
    <Simple>
      <Name>BPS</Name>
      <TagLanguage>eng</TagLanguage>
      <DefaultLanguage>1</DefaultLanguage>
      <String>128000</String>
    </Simple>
    <Simple>
      <Name>DURATION</Name>
      <TagLanguage>eng</TagLanguage>
      <DefaultLanguage>1</DefaultLanguage>
      <String>00:24:47.904000000</String>
    </Simple>
    <Simple>
      <Name>NUMBER_OF_FRAMES</Name>
      <TagLanguage>eng</TagLanguage>
      <DefaultLanguage>1</DefaultLanguage>
      <String>46497</String>
    </Simple>
    <Simple>
      <Name>NUMBER_OF_BYTES</Name>
      <TagLanguage>eng</TagLanguage>
      <DefaultLanguage>1</DefaultLanguage>
      <String>23806464</String>
    </Simple>
    <Simple>
      <Name>_STATISTICS_WRITING_APP</Name>
      <TagLanguage>eng</TagLanguage>
      <DefaultLanguage>1</DefaultLanguage>
      <String>mkvmerge v16.0.0 ('Protest') 32-bit</String>
    </Simple>
    <Simple>
      <Name>_STATISTICS_WRITING_DATE_UTC</Name>
      <TagLanguage>eng</TagLanguage>
      <DefaultLanguage>1</DefaultLanguage>
      <String>2018-03-04 11:43:23</String>
    </Simple>
    <Simple>
      <Name>_STATISTICS_TAGS</Name>
      <TagLanguage>eng</TagLanguage>
      <DefaultLanguage>1</DefaultLanguage>
      <String>BPS DURATION NUMBER_OF_FRAMES NUMBER_OF_BYTES</String>
    </Simple>
  </Tag>
  <Tag>
    <Targets>
      <TargetTypeValue>50</TargetTypeValue>
      <TrackUID>11416872681846500758</TrackUID>
      <TargetType>MOVIE</TargetType>
    </Targets>
    <Simple>
      <Name>BPS</Name>
      <TagLanguage>eng</TagLanguage>
      <DefaultLanguage>1</DefaultLanguage>
      <String>128000</String>
    </Simple>
    <Simple>
      <Name>DURATION</Name>
      <TagLanguage>eng</TagLanguage>
      <DefaultLanguage>1</DefaultLanguage>
      <String>00:24:47.904000000</String>
    </Simple>
    <Simple>
      <Name>NUMBER_OF_FRAMES</Name>
      <TagLanguage>eng</TagLanguage>
      <DefaultLanguage>1</DefaultLanguage>
      <String>46497</String>
    </Simple>
    <Simple>
      <Name>NUMBER_OF_BYTES</Name>
      <TagLanguage>eng</TagLanguage>
      <DefaultLanguage>1</DefaultLanguage>
      <String>23806464</String>
    </Simple>
    <Simple>
      <Name>_STATISTICS_WRITING_APP</Name>
      <TagLanguage>eng</TagLanguage>
      <DefaultLanguage>1</DefaultLanguage>
      <String>mkvmerge v16.0.0 ('Protest') 32-bit</String>
    </Simple>
    <Simple>
      <Name>_STATISTICS_WRITING_DATE_UTC</Name>
      <TagLanguage>eng</TagLanguage>
      <DefaultLanguage>1</DefaultLanguage>
      <String>2018-03-04 11:43:23</String>
    </Simple>
    <Simple>
      <Name>_STATISTICS_TAGS</Name>
      <TagLanguage>eng</TagLanguage>
      <DefaultLanguage>1</DefaultLanguage>
      <String>BPS DURATION NUMBER_OF_FRAMES NUMBER_OF_BYTES</String>
    </Simple>
  </Tag>
  <Tag>
    <Targets>
      <TargetTypeValue>50</TargetTypeValue>
      <TrackUID>6199862208389059462</TrackUID>
      <TargetType>MOVIE</TargetType>
    </Targets>
    <Simple>
      <Name>BPS</Name>
      <TagLanguage>eng</TagLanguage>
      <DefaultLanguage>1</DefaultLanguage>
      <String>4</String>
    </Simple>
    <Simple>
      <Name>DURATION</Name>
      <TagLanguage>eng</TagLanguage>
      <DefaultLanguage>1</DefaultLanguage>
      <String>00:01:15.075000000</String>
    </Simple>
    <Simple>
      <Name>NUMBER_OF_FRAMES</Name>
      <TagLanguage>eng</TagLanguage>
      <DefaultLanguage>1</DefaultLanguage>
      <String>2</String>
    </Simple>
    <Simple>
      <Name>NUMBER_OF_BYTES</Name>
      <TagLanguage>eng</TagLanguage>
      <DefaultLanguage>1</DefaultLanguage>
      <String>46</String>
    </Simple>
    <Simple>
      <Name>_STATISTICS_WRITING_APP</Name>
      <TagLanguage>eng</TagLanguage>
      <DefaultLanguage>1</DefaultLanguage>
      <String>mkvmerge v16.0.0 ('Protest') 32-bit</String>
    </Simple>
    <Simple>
      <Name>_STATISTICS_WRITING_DATE_UTC</Name>
      <TagLanguage>eng</TagLanguage>
      <DefaultLanguage>1</DefaultLanguage>
      <String>2018-03-04 11:43:23</String>
    </Simple>
    <Simple>
      <Name>_STATISTICS_TAGS</Name>
      <TagLanguage>eng</TagLanguage>
      <DefaultLanguage>1</DefaultLanguage>
      <String>BPS DURATION NUMBER_OF_FRAMES NUMBER_OF_BYTES</String>
    </Simple>
  </Tag>
  <Tag>
    <Targets>
      <TargetTypeValue>50</TargetTypeValue>
      <TrackUID>7447327162102742457</TrackUID>
      <TargetType>MOVIE</TargetType>
    </Targets>
    <Simple>
      <Name>BPS</Name>
      <TagLanguage>eng</TagLanguage>
      <DefaultLanguage>1</DefaultLanguage>
      <String>72</String>
    </Simple>
    <Simple>
      <Name>DURATION</Name>
      <TagLanguage>eng</TagLanguage>
      <DefaultLanguage>1</DefaultLanguage>
      <String>00:22:08.694000000</String>
    </Simple>
    <Simple>
      <Name>NUMBER_OF_FRAMES</Name>
      <TagLanguage>eng</TagLanguage>
      <DefaultLanguage>1</DefaultLanguage>
      <String>347</String>
    </Simple>
    <Simple>
      <Name>NUMBER_OF_BYTES</Name>
      <TagLanguage>eng</TagLanguage>
      <DefaultLanguage>1</DefaultLanguage>
      <String>12067</String>
    </Simple>
    <Simple>
      <Name>_STATISTICS_WRITING_APP</Name>
      <TagLanguage>eng</TagLanguage>
      <DefaultLanguage>1</DefaultLanguage>
      <String>mkvmerge v16.0.0 ('Protest') 32-bit</String>
    </Simple>
    <Simple>
      <Name>_STATISTICS_WRITING_DATE_UTC</Name>
      <TagLanguage>eng</TagLanguage>
      <DefaultLanguage>1</DefaultLanguage>
      <String>2018-03-04 11:43:23</String>
    </Simple>
    <Simple>
      <Name>_STATISTICS_TAGS</Name>
      <TagLanguage>eng</TagLanguage>
      <DefaultLanguage>1</DefaultLanguage>
      <String>BPS DURATION NUMBER_OF_FRAMES NUMBER_OF_BYTES</String>
    </Simple>
  </Tag>
  <Tag>
    <Targets>
      <TargetTypeValue>50</TargetTypeValue>
      <TrackUID>10859314265692513203</TrackUID>
      <TargetType>MOVIE</TargetType>
    </Targets>
    <Simple>
      <Name>BPS</Name>
      <TagLanguage>eng</TagLanguage>
      <DefaultLanguage>1</DefaultLanguage>
      <String>2</String>
    </Simple>
    <Simple>
      <Name>DURATION</Name>
      <TagLanguage>eng</TagLanguage>
      <DefaultLanguage>1</DefaultLanguage>
      <String>00:03:33.921000000</String>
    </Simple>
    <Simple>
      <Name>NUMBER_OF_FRAMES</Name>
      <TagLanguage>eng</TagLanguage>
      <DefaultLanguage>1</DefaultLanguage>
      <String>2</String>
    </Simple>
    <Simple>
      <Name>NUMBER_OF_BYTES</Name>
      <TagLanguage>eng</TagLanguage>
      <DefaultLanguage>1</DefaultLanguage>
      <String>58</String>
    </Simple>
    <Simple>
      <Name>_STATISTICS_WRITING_APP</Name>
      <TagLanguage>eng</TagLanguage>
      <DefaultLanguage>1</DefaultLanguage>
      <String>mkvmerge v16.0.0 ('Protest') 32-bit</String>
    </Simple>
    <Simple>
      <Name>_STATISTICS_WRITING_DATE_UTC</Name>
      <TagLanguage>eng</TagLanguage>
      <DefaultLanguage>1</DefaultLanguage>
      <String>2018-03-04 11:43:23</String>
    </Simple>
    <Simple>
      <Name>_STATISTICS_TAGS</Name>
      <TagLanguage>eng</TagLanguage>
      <DefaultLanguage>1</DefaultLanguage>
      <String>BPS DURATION NUMBER_OF_FRAMES NUMBER_OF_BYTES</String>
    </Simple>
  </Tag>
  <Tag>
    <Targets>
      <TargetTypeValue>50</TargetTypeValue>
      <TrackUID>13512442462074808738</TrackUID>
      <TargetType>MOVIE</TargetType>
    </Targets>
    <Simple>
      <Name>BPS</Name>
      <TagLanguage>eng</TagLanguage>
      <DefaultLanguage>1</DefaultLanguage>
      <String>72</String>
    </Simple>
    <Simple>
      <Name>DURATION</Name>
      <TagLanguage>eng</TagLanguage>
      <DefaultLanguage>1</DefaultLanguage>
      <String>00:22:18.704000000</String>
    </Simple>
    <Simple>
      <Name>NUMBER_OF_FRAMES</Name>
      <TagLanguage>eng</TagLanguage>
      <DefaultLanguage>1</DefaultLanguage>
      <String>348</String>
    </Simple>
    <Simple>
      <Name>NUMBER_OF_BYTES</Name>
      <TagLanguage>eng</TagLanguage>
      <DefaultLanguage>1</DefaultLanguage>
      <String>12168</String>
    </Simple>
    <Simple>
      <Name>_STATISTICS_WRITING_APP</Name>
      <TagLanguage>eng</TagLanguage>
      <DefaultLanguage>1</DefaultLanguage>
      <String>mkvmerge v16.0.0 ('Protest') 32-bit</String>
    </Simple>
    <Simple>
      <Name>_STATISTICS_WRITING_DATE_UTC</Name>
      <TagLanguage>eng</TagLanguage>
      <DefaultLanguage>1</DefaultLanguage>
      <String>2018-03-04 11:43:23</String>
    </Simple>
    <Simple>
      <Name>_STATISTICS_TAGS</Name>
      <TagLanguage>eng</TagLanguage>
      <DefaultLanguage>1</DefaultLanguage>
      <String>BPS DURATION NUMBER_OF_FRAMES NUMBER_OF_BYTES</String>
    </Simple>
  </Tag>
  <Tag>
    <Targets>
      <TargetTypeValue>50</TargetTypeValue>
      <TrackUID>3958789467928305850</TrackUID>
      <TargetType>MOVIE</TargetType>
    </Targets>
    <Simple>
      <Name>BPS</Name>
      <TagLanguage>eng</TagLanguage>
      <DefaultLanguage>1</DefaultLanguage>
      <String>59</String>
    </Simple>
    <Simple>
      <Name>DURATION</Name>
      <TagLanguage>eng</TagLanguage>
      <DefaultLanguage>1</DefaultLanguage>
      <String>00:00:03.921000000</String>
    </Simple>
    <Simple>
      <Name>NUMBER_OF_FRAMES</Name>
      <TagLanguage>eng</TagLanguage>
      <DefaultLanguage>1</DefaultLanguage>
      <String>1</String>
    </Simple>
    <Simple>
      <Name>NUMBER_OF_BYTES</Name>
      <TagLanguage>eng</TagLanguage>
      <DefaultLanguage>1</DefaultLanguage>
      <String>29</String>
    </Simple>
    <Simple>
      <Name>_STATISTICS_WRITING_APP</Name>
      <TagLanguage>eng</TagLanguage>
      <DefaultLanguage>1</DefaultLanguage>
      <String>mkvmerge v16.0.0 ('Protest') 32-bit</String>
    </Simple>
    <Simple>
      <Name>_STATISTICS_WRITING_DATE_UTC</Name>
      <TagLanguage>eng</TagLanguage>
      <DefaultLanguage>1</DefaultLanguage>
      <String>2018-03-04 11:43:23</String>
    </Simple>
    <Simple>
      <Name>_STATISTICS_TAGS</Name>
      <TagLanguage>eng</TagLanguage>
      <DefaultLanguage>1</DefaultLanguage>
      <String>BPS DURATION NUMBER_OF_FRAMES NUMBER_OF_BYTES</String>
    </Simple>
  </Tag>
  <Tag>
    <Targets>
      <TargetTypeValue>50</TargetTypeValue>
      <TrackUID>5431934967233819320</TrackUID>
      <TargetType>MOVIE</TargetType>
    </Targets>
    <Simple>
      <Name>BPS</Name>
      <TagLanguage>eng</TagLanguage>
      <DefaultLanguage>1</DefaultLanguage>
      <String>77</String>
    </Simple>
    <Simple>
      <Name>DURATION</Name>
      <TagLanguage>eng</TagLanguage>
      <DefaultLanguage>1</DefaultLanguage>
      <String>00:22:18.704000000</String>
    </Simple>
    <Simple>
      <Name>NUMBER_OF_FRAMES</Name>
      <TagLanguage>eng</TagLanguage>
      <DefaultLanguage>1</DefaultLanguage>
      <String>348</String>
    </Simple>
    <Simple>
      <Name>NUMBER_OF_BYTES</Name>
      <TagLanguage>eng</TagLanguage>
      <DefaultLanguage>1</DefaultLanguage>
      <String>12977</String>
    </Simple>
    <Simple>
      <Name>_STATISTICS_WRITING_APP</Name>
      <TagLanguage>eng</TagLanguage>
      <DefaultLanguage>1</DefaultLanguage>
      <String>mkvmerge v16.0.0 ('Protest') 32-bit</String>
    </Simple>
    <Simple>
      <Name>_STATISTICS_WRITING_DATE_UTC</Name>
      <TagLanguage>eng</TagLanguage>
      <DefaultLanguage>1</DefaultLanguage>
      <String>2018-03-04 11:43:23</String>
    </Simple>
    <Simple>
      <Name>_STATISTICS_TAGS</Name>
      <TagLanguage>eng</TagLanguage>
      <DefaultLanguage>1</DefaultLanguage>
      <String>BPS DURATION NUMBER_OF_FRAMES NUMBER_OF_BYTES</String>
    </Simple>
  </Tag>
  <Tag>
    <Targets>
      <TargetTypeValue>50</TargetTypeValue>
      <TrackUID>13235476721947937968</TrackUID>
      <TargetType>MOVIE</TargetType>
    </Targets>
    <Simple>
      <Name>BPS</Name>
      <TagLanguage>eng</TagLanguage>
      <DefaultLanguage>1</DefaultLanguage>
      <String>1</String>
    </Simple>
    <Simple>
      <Name>DURATION</Name>
      <TagLanguage>eng</TagLanguage>
      <DefaultLanguage>1</DefaultLanguage>
      <String>00:03:33.921000000</String>
    </Simple>
    <Simple>
      <Name>NUMBER_OF_FRAMES</Name>
      <TagLanguage>eng</TagLanguage>
      <DefaultLanguage>1</DefaultLanguage>
      <String>2</String>
    </Simple>
    <Simple>
      <Name>NUMBER_OF_BYTES</Name>
      <TagLanguage>eng</TagLanguage>
      <DefaultLanguage>1</DefaultLanguage>
      <String>51</String>
    </Simple>
    <Simple>
      <Name>_STATISTICS_WRITING_APP</Name>
      <TagLanguage>eng</TagLanguage>
      <DefaultLanguage>1</DefaultLanguage>
      <String>mkvmerge v16.0.0 ('Protest') 32-bit</String>
    </Simple>
    <Simple>
      <Name>_STATISTICS_WRITING_DATE_UTC</Name>
      <TagLanguage>eng</TagLanguage>
      <DefaultLanguage>1</DefaultLanguage>
      <String>2018-03-04 11:43:23</String>
    </Simple>
    <Simple>
      <Name>_STATISTICS_TAGS</Name>
      <TagLanguage>eng</TagLanguage>
      <DefaultLanguage>1</DefaultLanguage>
      <String>BPS DURATION NUMBER_OF_FRAMES NUMBER_OF_BYTES</String>
    </Simple>
  </Tag>
  <Tag>
    <Targets>
      <TargetTypeValue>50</TargetTypeValue>
      <TrackUID>12707727083015396486</TrackUID>
      <TargetType>MOVIE</TargetType>
    </Targets>
    <Simple>
      <Name>BPS</Name>
      <TagLanguage>eng</TagLanguage>
      <DefaultLanguage>1</DefaultLanguage>
      <String>76</String>
    </Simple>
    <Simple>
      <Name>DURATION</Name>
      <TagLanguage>eng</TagLanguage>
      <DefaultLanguage>1</DefaultLanguage>
      <String>00:22:18.704000000</String>
    </Simple>
    <Simple>
      <Name>NUMBER_OF_FRAMES</Name>
      <TagLanguage>eng</TagLanguage>
      <DefaultLanguage>1</DefaultLanguage>
      <String>351</String>
    </Simple>
    <Simple>
      <Name>NUMBER_OF_BYTES</Name>
      <TagLanguage>eng</TagLanguage>
      <DefaultLanguage>1</DefaultLanguage>
      <String>12823</String>
    </Simple>
    <Simple>
      <Name>_STATISTICS_WRITING_APP</Name>
      <TagLanguage>eng</TagLanguage>
      <DefaultLanguage>1</DefaultLanguage>
      <String>mkvmerge v16.0.0 ('Protest') 32-bit</String>
    </Simple>
    <Simple>
      <Name>_STATISTICS_WRITING_DATE_UTC</Name>
      <TagLanguage>eng</TagLanguage>
      <DefaultLanguage>1</DefaultLanguage>
      <String>2018-03-04 11:43:23</String>
    </Simple>
    <Simple>
      <Name>_STATISTICS_TAGS</Name>
      <TagLanguage>eng</TagLanguage>
      <DefaultLanguage>1</DefaultLanguage>
      <String>BPS DURATION NUMBER_OF_FRAMES NUMBER_OF_BYTES</String>
    </Simple>
  </Tag>
  <Tag>
    <Targets>
      <TargetTypeValue>50</TargetTypeValue>
      <TrackUID>11762970253312070037</TrackUID>
      <TargetType>MOVIE</TargetType>
    </Targets>
    <Simple>
      <Name>BPS</Name>
      <TagLanguage>eng</TagLanguage>
      <DefaultLanguage>1</DefaultLanguage>
      <String>2</String>
    </Simple>
    <Simple>
      <Name>DURATION</Name>
      <TagLanguage>eng</TagLanguage>
      <DefaultLanguage>1</DefaultLanguage>
      <String>00:03:33.921000000</String>
    </Simple>
    <Simple>
      <Name>NUMBER_OF_FRAMES</Name>
      <TagLanguage>eng</TagLanguage>
      <DefaultLanguage>1</DefaultLanguage>
      <String>2</String>
    </Simple>
    <Simple>
      <Name>NUMBER_OF_BYTES</Name>
      <TagLanguage>eng</TagLanguage>
      <DefaultLanguage>1</DefaultLanguage>
      <String>55</String>
    </Simple>
    <Simple>
      <Name>_STATISTICS_WRITING_APP</Name>
      <TagLanguage>eng</TagLanguage>
      <DefaultLanguage>1</DefaultLanguage>
      <String>mkvmerge v16.0.0 ('Protest') 32-bit</String>
    </Simple>
    <Simple>
      <Name>_STATISTICS_WRITING_DATE_UTC</Name>
      <TagLanguage>eng</TagLanguage>
      <DefaultLanguage>1</DefaultLanguage>
      <String>2018-03-04 11:43:23</String>
    </Simple>
    <Simple>
      <Name>_STATISTICS_TAGS</Name>
      <TagLanguage>eng</TagLanguage>
      <DefaultLanguage>1</DefaultLanguage>
      <String>BPS DURATION NUMBER_OF_FRAMES NUMBER_OF_BYTES</String>
    </Simple>
  </Tag>
  <Tag>
    <Targets>
      <TargetTypeValue>50</TargetTypeValue>
      <TrackUID>14835340932230639284</TrackUID>
      <TargetType>MOVIE</TargetType>
    </Targets>
    <Simple>
      <Name>BPS</Name>
      <TagLanguage>eng</TagLanguage>
      <DefaultLanguage>1</DefaultLanguage>
      <String>82</String>
    </Simple>
    <Simple>
      <Name>DURATION</Name>
      <TagLanguage>eng</TagLanguage>
      <DefaultLanguage>1</DefaultLanguage>
      <String>00:22:18.704000000</String>
    </Simple>
    <Simple>
      <Name>NUMBER_OF_FRAMES</Name>
      <TagLanguage>eng</TagLanguage>
      <DefaultLanguage>1</DefaultLanguage>
      <String>353</String>
    </Simple>
    <Simple>
      <Name>NUMBER_OF_BYTES</Name>
      <TagLanguage>eng</TagLanguage>
      <DefaultLanguage>1</DefaultLanguage>
      <String>13797</String>
    </Simple>
    <Simple>
      <Name>_STATISTICS_WRITING_APP</Name>
      <TagLanguage>eng</TagLanguage>
      <DefaultLanguage>1</DefaultLanguage>
      <String>mkvmerge v16.0.0 ('Protest') 32-bit</String>
    </Simple>
    <Simple>
      <Name>_STATISTICS_WRITING_DATE_UTC</Name>
      <TagLanguage>eng</TagLanguage>
      <DefaultLanguage>1</DefaultLanguage>
      <String>2018-03-04 11:43:23</String>
    </Simple>
    <Simple>
      <Name>_STATISTICS_TAGS</Name>
      <TagLanguage>eng</TagLanguage>
      <DefaultLanguage>1</DefaultLanguage>
      <String>BPS DURATION NUMBER_OF_FRAMES NUMBER_OF_BYTES</String>
    </Simple>
  </Tag>
  <Tag>
    <Targets>
      <TargetTypeValue>50</TargetTypeValue>
      <TrackUID>7071337159333620866</TrackUID>
      <TargetType>MOVIE</TargetType>
    </Targets>
    <Simple>
      <Name>BPS</Name>
      <TagLanguage>eng</TagLanguage>
      <DefaultLanguage>1</DefaultLanguage>
      <String>2</String>
    </Simple>
    <Simple>
      <Name>DURATION</Name>
      <TagLanguage>eng</TagLanguage>
      <DefaultLanguage>1</DefaultLanguage>
      <String>00:03:33.921000000</String>
    </Simple>
    <Simple>
      <Name>NUMBER_OF_FRAMES</Name>
      <TagLanguage>eng</TagLanguage>
      <DefaultLanguage>1</DefaultLanguage>
      <String>2</String>
    </Simple>
    <Simple>
      <Name>NUMBER_OF_BYTES</Name>
      <TagLanguage>eng</TagLanguage>
      <DefaultLanguage>1</DefaultLanguage>
      <String>56</String>
    </Simple>
    <Simple>
      <Name>_STATISTICS_WRITING_APP</Name>
      <TagLanguage>eng</TagLanguage>
      <DefaultLanguage>1</DefaultLanguage>
      <String>mkvmerge v16.0.0 ('Protest') 32-bit</String>
    </Simple>
    <Simple>
      <Name>_STATISTICS_WRITING_DATE_UTC</Name>
      <TagLanguage>eng</TagLanguage>
      <DefaultLanguage>1</DefaultLanguage>
      <String>2018-03-04 11:43:23</String>
    </Simple>
    <Simple>
      <Name>_STATISTICS_TAGS</Name>
      <TagLanguage>eng</TagLanguage>
      <DefaultLanguage>1</DefaultLanguage>
      <String>BPS DURATION NUMBER_OF_FRAMES NUMBER_OF_BYTES</String>
    </Simple>
  </Tag>
  <Tag>
    <Targets>
      <TargetTypeValue>50</TargetTypeValue>
      <TrackUID>13913591341469255865</TrackUID>
      <TargetType>MOVIE</TargetType>
    </Targets>
    <Simple>
      <Name>BPS</Name>
      <TagLanguage>eng</TagLanguage>
      <DefaultLanguage>1</DefaultLanguage>
      <String>76</String>
    </Simple>
    <Simple>
      <Name>DURATION</Name>
      <TagLanguage>eng</TagLanguage>
      <DefaultLanguage>1</DefaultLanguage>
      <String>00:22:18.704000000</String>
    </Simple>
    <Simple>
      <Name>NUMBER_OF_FRAMES</Name>
      <TagLanguage>eng</TagLanguage>
      <DefaultLanguage>1</DefaultLanguage>
      <String>348</String>
    </Simple>
    <Simple>
      <Name>NUMBER_OF_BYTES</Name>
      <TagLanguage>eng</TagLanguage>
      <DefaultLanguage>1</DefaultLanguage>
      <String>12747</String>
    </Simple>
    <Simple>
      <Name>_STATISTICS_WRITING_APP</Name>
      <TagLanguage>eng</TagLanguage>
      <DefaultLanguage>1</DefaultLanguage>
      <String>mkvmerge v16.0.0 ('Protest') 32-bit</String>
    </Simple>
    <Simple>
      <Name>_STATISTICS_WRITING_DATE_UTC</Name>
      <TagLanguage>eng</TagLanguage>
      <DefaultLanguage>1</DefaultLanguage>
      <String>2018-03-04 11:43:23</String>
    </Simple>
    <Simple>
      <Name>_STATISTICS_TAGS</Name>
      <TagLanguage>eng</TagLanguage>
      <DefaultLanguage>1</DefaultLanguage>
      <String>BPS DURATION NUMBER_OF_FRAMES NUMBER_OF_BYTES</String>
    </Simple>
  </Tag>
  <Tag>
    <Targets>
      <TargetTypeValue>50</TargetTypeValue>
      <TrackUID>4112105380874167446</TrackUID>
      <TargetType>MOVIE</TargetType>
    </Targets>
    <Simple>
      <Name>BPS</Name>
      <TagLanguage>eng</TagLanguage>
      <DefaultLanguage>1</DefaultLanguage>
      <String>72</String>
    </Simple>
    <Simple>
      <Name>DURATION</Name>
      <TagLanguage>eng</TagLanguage>
      <DefaultLanguage>1</DefaultLanguage>
      <String>00:22:18.704000000</String>
    </Simple>
    <Simple>
      <Name>NUMBER_OF_FRAMES</Name>
      <TagLanguage>eng</TagLanguage>
      <DefaultLanguage>1</DefaultLanguage>
      <String>348</String>
    </Simple>
    <Simple>
      <Name>NUMBER_OF_BYTES</Name>
      <TagLanguage>eng</TagLanguage>
      <DefaultLanguage>1</DefaultLanguage>
      <String>12194</String>
    </Simple>
    <Simple>
      <Name>_STATISTICS_WRITING_APP</Name>
      <TagLanguage>eng</TagLanguage>
      <DefaultLanguage>1</DefaultLanguage>
      <String>mkvmerge v16.0.0 ('Protest') 32-bit</String>
    </Simple>
    <Simple>
      <Name>_STATISTICS_WRITING_DATE_UTC</Name>
      <TagLanguage>eng</TagLanguage>
      <DefaultLanguage>1</DefaultLanguage>
      <String>2018-03-04 11:43:23</String>
    </Simple>
    <Simple>
      <Name>_STATISTICS_TAGS</Name>
      <TagLanguage>eng</TagLanguage>
      <DefaultLanguage>1</DefaultLanguage>
      <String>BPS DURATION NUMBER_OF_FRAMES NUMBER_OF_BYTES</String>
    </Simple>
  </Tag>
  <Tag>
    <Targets>
      <TargetTypeValue>50</TargetTypeValue>
      <TrackUID>12870700374581301942</TrackUID>
      <TargetType>MOVIE</TargetType>
    </Targets>
    <Simple>
      <Name>BPS</Name>
      <TagLanguage>eng</TagLanguage>
      <DefaultLanguage>1</DefaultLanguage>
      <String>1</String>
    </Simple>
    <Simple>
      <Name>DURATION</Name>
      <TagLanguage>eng</TagLanguage>
      <DefaultLanguage>1</DefaultLanguage>
      <String>00:03:33.921000000</String>
    </Simple>
    <Simple>
      <Name>NUMBER_OF_FRAMES</Name>
      <TagLanguage>eng</TagLanguage>
      <DefaultLanguage>1</DefaultLanguage>
      <String>2</String>
    </Simple>
    <Simple>
      <Name>NUMBER_OF_BYTES</Name>
      <TagLanguage>eng</TagLanguage>
      <DefaultLanguage>1</DefaultLanguage>
      <String>49</String>
    </Simple>
    <Simple>
      <Name>_STATISTICS_WRITING_APP</Name>
      <TagLanguage>eng</TagLanguage>
      <DefaultLanguage>1</DefaultLanguage>
      <String>mkvmerge v16.0.0 ('Protest') 32-bit</String>
    </Simple>
    <Simple>
      <Name>_STATISTICS_WRITING_DATE_UTC</Name>
      <TagLanguage>eng</TagLanguage>
      <DefaultLanguage>1</DefaultLanguage>
      <String>2018-03-04 11:43:23</String>
    </Simple>
    <Simple>
      <Name>_STATISTICS_TAGS</Name>
      <TagLanguage>eng</TagLanguage>
      <DefaultLanguage>1</DefaultLanguage>
      <String>BPS DURATION NUMBER_OF_FRAMES NUMBER_OF_BYTES</String>
    </Simple>
  </Tag>
  <Tag>
    <Targets>
      <TargetTypeValue>50</TargetTypeValue>
      <TrackUID>6296011085846126484</TrackUID>
      <TargetType>MOVIE</TargetType>
    </Targets>
    <Simple>
      <Name>BPS</Name>
      <TagLanguage>eng</TagLanguage>
      <DefaultLanguage>1</DefaultLanguage>
      <String>73</String>
    </Simple>
    <Simple>
      <Name>DURATION</Name>
      <TagLanguage>eng</TagLanguage>
      <DefaultLanguage>1</DefaultLanguage>
      <String>00:22:18.704000000</String>
    </Simple>
    <Simple>
      <Name>NUMBER_OF_FRAMES</Name>
      <TagLanguage>eng</TagLanguage>
      <DefaultLanguage>1</DefaultLanguage>
      <String>332</String>
    </Simple>
    <Simple>
      <Name>NUMBER_OF_BYTES</Name>
      <TagLanguage>eng</TagLanguage>
      <DefaultLanguage>1</DefaultLanguage>
      <String>12292</String>
    </Simple>
    <Simple>
      <Name>_STATISTICS_WRITING_APP</Name>
      <TagLanguage>eng</TagLanguage>
      <DefaultLanguage>1</DefaultLanguage>
      <String>mkvmerge v16.0.0 ('Protest') 32-bit</String>
    </Simple>
    <Simple>
      <Name>_STATISTICS_WRITING_DATE_UTC</Name>
      <TagLanguage>eng</TagLanguage>
      <DefaultLanguage>1</DefaultLanguage>
      <String>2018-03-04 11:43:23</String>
    </Simple>
    <Simple>
      <Name>_STATISTICS_TAGS</Name>
      <TagLanguage>eng</TagLanguage>
      <DefaultLanguage>1</DefaultLanguage>
      <String>BPS DURATION NUMBER_OF_FRAMES NUMBER_OF_BYTES</String>
    </Simple>
  </Tag>
  <Tag>
    <Targets>
      <TargetTypeValue>50</TargetTypeValue>
      <TrackUID>10068063223248899987</TrackUID>
      <TargetType>MOVIE</TargetType>
    </Targets>
    <Simple>
      <Name>BPS</Name>
      <TagLanguage>eng</TagLanguage>
      <DefaultLanguage>1</DefaultLanguage>
      <String>2</String>
    </Simple>
    <Simple>
      <Name>DURATION</Name>
      <TagLanguage>eng</TagLanguage>
      <DefaultLanguage>1</DefaultLanguage>
      <String>00:03:33.814000000</String>
    </Simple>
    <Simple>
      <Name>NUMBER_OF_FRAMES</Name>
      <TagLanguage>eng</TagLanguage>
      <DefaultLanguage>1</DefaultLanguage>
      <String>2</String>
    </Simple>
    <Simple>
      <Name>NUMBER_OF_BYTES</Name>
      <TagLanguage>eng</TagLanguage>
      <DefaultLanguage>1</DefaultLanguage>
      <String>56</String>
    </Simple>
    <Simple>
      <Name>_STATISTICS_WRITING_APP</Name>
      <TagLanguage>eng</TagLanguage>
      <DefaultLanguage>1</DefaultLanguage>
      <String>mkvmerge v16.0.0 ('Protest') 32-bit</String>
    </Simple>
    <Simple>
      <Name>_STATISTICS_WRITING_DATE_UTC</Name>
      <TagLanguage>eng</TagLanguage>
      <DefaultLanguage>1</DefaultLanguage>
      <String>2018-03-04 11:43:23</String>
    </Simple>
    <Simple>
      <Name>_STATISTICS_TAGS</Name>
      <TagLanguage>eng</TagLanguage>
      <DefaultLanguage>1</DefaultLanguage>
      <String>BPS DURATION NUMBER_OF_FRAMES NUMBER_OF_BYTES</String>
    </Simple>
  </Tag>
  <Tag>
    <Targets>
      <TargetTypeValue>50</TargetTypeValue>
      <TrackUID>14336046189360678558</TrackUID>
      <TargetType>MOVIE</TargetType>
    </Targets>
    <Simple>
      <Name>BPS</Name>
      <TagLanguage>eng</TagLanguage>
      <DefaultLanguage>1</DefaultLanguage>
      <String>56</String>
    </Simple>
    <Simple>
      <Name>DURATION</Name>
      <TagLanguage>eng</TagLanguage>
      <DefaultLanguage>1</DefaultLanguage>
      <String>00:24:06.779000000</String>
    </Simple>
    <Simple>
      <Name>NUMBER_OF_FRAMES</Name>
      <TagLanguage>eng</TagLanguage>
      <DefaultLanguage>1</DefaultLanguage>
      <String>350</String>
    </Simple>
    <Simple>
      <Name>NUMBER_OF_BYTES</Name>
      <TagLanguage>eng</TagLanguage>
      <DefaultLanguage>1</DefaultLanguage>
      <String>10183</String>
    </Simple>
    <Simple>
      <Name>_STATISTICS_WRITING_APP</Name>
      <TagLanguage>eng</TagLanguage>
      <DefaultLanguage>1</DefaultLanguage>
      <String>mkvmerge v16.0.0 ('Protest') 32-bit</String>
    </Simple>
    <Simple>
      <Name>_STATISTICS_WRITING_DATE_UTC</Name>
      <TagLanguage>eng</TagLanguage>
      <DefaultLanguage>1</DefaultLanguage>
      <String>2018-03-04 11:43:23</String>
    </Simple>
    <Simple>
      <Name>_STATISTICS_TAGS</Name>
      <TagLanguage>eng</TagLanguage>
      <DefaultLanguage>1</DefaultLanguage>
      <String>BPS DURATION NUMBER_OF_FRAMES NUMBER_OF_BYTES</String>
    </Simple>
  </Tag>
  <Tag>
    <Targets>
      <TargetTypeValue>50</TargetTypeValue>
      <TrackUID>14672729751906631050</TrackUID>
      <TargetType>MOVIE</TargetType>
    </Targets>
    <Simple>
      <Name>BPS</Name>
      <TagLanguage>eng</TagLanguage>
      <DefaultLanguage>1</DefaultLanguage>
      <String>1</String>
    </Simple>
    <Simple>
      <Name>DURATION</Name>
      <TagLanguage>eng</TagLanguage>
      <DefaultLanguage>1</DefaultLanguage>
      <String>00:03:33.814000000</String>
    </Simple>
    <Simple>
      <Name>NUMBER_OF_FRAMES</Name>
      <TagLanguage>eng</TagLanguage>
      <DefaultLanguage>1</DefaultLanguage>
      <String>2</String>
    </Simple>
    <Simple>
      <Name>NUMBER_OF_BYTES</Name>
      <TagLanguage>eng</TagLanguage>
      <DefaultLanguage>1</DefaultLanguage>
      <String>52</String>
    </Simple>
    <Simple>
      <Name>_STATISTICS_WRITING_APP</Name>
      <TagLanguage>eng</TagLanguage>
      <DefaultLanguage>1</DefaultLanguage>
      <String>mkvmerge v16.0.0 ('Protest') 32-bit</String>
    </Simple>
    <Simple>
      <Name>_STATISTICS_WRITING_DATE_UTC</Name>
      <TagLanguage>eng</TagLanguage>
      <DefaultLanguage>1</DefaultLanguage>
      <String>2018-03-04 11:43:23</String>
    </Simple>
    <Simple>
      <Name>_STATISTICS_TAGS</Name>
      <TagLanguage>eng</TagLanguage>
      <DefaultLanguage>1</DefaultLanguage>
      <String>BPS DURATION NUMBER_OF_FRAMES NUMBER_OF_BYTES</String>
    </Simple>
  </Tag>
  <Tag>
    <Targets>
      <TargetTypeValue>50</TargetTypeValue>
      <TrackUID>13431278673786602671</TrackUID>
      <TargetType>MOVIE</TargetType>
    </Targets>
    <Simple>
      <Name>BPS</Name>
      <TagLanguage>eng</TagLanguage>
      <DefaultLanguage>1</DefaultLanguage>
      <String>69</String>
    </Simple>
    <Simple>
      <Name>DURATION</Name>
      <TagLanguage>eng</TagLanguage>
      <DefaultLanguage>1</DefaultLanguage>
      <String>00:22:18.704000000</String>
    </Simple>
    <Simple>
      <Name>NUMBER_OF_FRAMES</Name>
      <TagLanguage>eng</TagLanguage>
      <DefaultLanguage>1</DefaultLanguage>
      <String>348</String>
    </Simple>
    <Simple>
      <Name>NUMBER_OF_BYTES</Name>
      <TagLanguage>eng</TagLanguage>
      <DefaultLanguage>1</DefaultLanguage>
      <String>11658</String>
    </Simple>
    <Simple>
      <Name>_STATISTICS_WRITING_APP</Name>
      <TagLanguage>eng</TagLanguage>
      <DefaultLanguage>1</DefaultLanguage>
      <String>mkvmerge v16.0.0 ('Protest') 32-bit</String>
    </Simple>
    <Simple>
      <Name>_STATISTICS_WRITING_DATE_UTC</Name>
      <TagLanguage>eng</TagLanguage>
      <DefaultLanguage>1</DefaultLanguage>
      <String>2018-03-04 11:43:23</String>
    </Simple>
    <Simple>
      <Name>_STATISTICS_TAGS</Name>
      <TagLanguage>eng</TagLanguage>
      <DefaultLanguage>1</DefaultLanguage>
      <String>BPS DURATION NUMBER_OF_FRAMES NUMBER_OF_BYTES</String>
    </Simple>
  </Tag>
  <Tag>
    <Targets>
      <TargetTypeValue>50</TargetTypeValue>
      <TrackUID>8452863550537001633</TrackUID>
      <TargetType>MOVIE</TargetType>
    </Targets>
    <Simple>
      <Name>BPS</Name>
      <TagLanguage>eng</TagLanguage>
      <DefaultLanguage>1</DefaultLanguage>
      <String>74</String>
    </Simple>
    <Simple>
      <Name>DURATION</Name>
      <TagLanguage>eng</TagLanguage>
      <DefaultLanguage>1</DefaultLanguage>
      <String>00:22:18.704000000</String>
    </Simple>
    <Simple>
      <Name>NUMBER_OF_FRAMES</Name>
      <TagLanguage>eng</TagLanguage>
      <DefaultLanguage>1</DefaultLanguage>
      <String>331</String>
    </Simple>
    <Simple>
      <Name>NUMBER_OF_BYTES</Name>
      <TagLanguage>eng</TagLanguage>
      <DefaultLanguage>1</DefaultLanguage>
      <String>12498</String>
    </Simple>
    <Simple>
      <Name>_STATISTICS_WRITING_APP</Name>
      <TagLanguage>eng</TagLanguage>
      <DefaultLanguage>1</DefaultLanguage>
      <String>mkvmerge v16.0.0 ('Protest') 32-bit</String>
    </Simple>
    <Simple>
      <Name>_STATISTICS_WRITING_DATE_UTC</Name>
      <TagLanguage>eng</TagLanguage>
      <DefaultLanguage>1</DefaultLanguage>
      <String>2018-03-04 11:43:23</String>
    </Simple>
    <Simple>
      <Name>_STATISTICS_TAGS</Name>
      <TagLanguage>eng</TagLanguage>
      <DefaultLanguage>1</DefaultLanguage>
      <String>BPS DURATION NUMBER_OF_FRAMES NUMBER_OF_BYTES</String>
    </Simple>
  </Tag>
  <Tag>
    <Targets>
      <TargetTypeValue>50</TargetTypeValue>
      <TrackUID>1602992342242836914</TrackUID>
      <TargetType>MOVIE</TargetType>
    </Targets>
    <Simple>
      <Name>BPS</Name>
      <TagLanguage>eng</TagLanguage>
      <DefaultLanguage>1</DefaultLanguage>
      <String>65</String>
    </Simple>
    <Simple>
      <Name>DURATION</Name>
      <TagLanguage>eng</TagLanguage>
      <DefaultLanguage>1</DefaultLanguage>
      <String>00:22:18.704000000</String>
    </Simple>
    <Simple>
      <Name>NUMBER_OF_FRAMES</Name>
      <TagLanguage>eng</TagLanguage>
      <DefaultLanguage>1</DefaultLanguage>
      <String>348</String>
    </Simple>
    <Simple>
      <Name>NUMBER_OF_BYTES</Name>
      <TagLanguage>eng</TagLanguage>
      <DefaultLanguage>1</DefaultLanguage>
      <String>11018</String>
    </Simple>
    <Simple>
      <Name>_STATISTICS_WRITING_APP</Name>
      <TagLanguage>eng</TagLanguage>
      <DefaultLanguage>1</DefaultLanguage>
      <String>mkvmerge v16.0.0 ('Protest') 32-bit</String>
    </Simple>
    <Simple>
      <Name>_STATISTICS_WRITING_DATE_UTC</Name>
      <TagLanguage>eng</TagLanguage>
      <DefaultLanguage>1</DefaultLanguage>
      <String>2018-03-04 11:43:23</String>
    </Simple>
    <Simple>
      <Name>_STATISTICS_TAGS</Name>
      <TagLanguage>eng</TagLanguage>
      <DefaultLanguage>1</DefaultLanguage>
      <String>BPS DURATION NUMBER_OF_FRAMES NUMBER_OF_BYTES</String>
    </Simple>
  </Tag>
  <Tag>
    <Targets>
      <TargetTypeValue>50</TargetTypeValue>
      <TrackUID>1040345216088560025</TrackUID>
      <TargetType>MOVIE</TargetType>
    </Targets>
    <Simple>
      <Name>BPS</Name>
      <TagLanguage>eng</TagLanguage>
      <DefaultLanguage>1</DefaultLanguage>
      <String>72</String>
    </Simple>
    <Simple>
      <Name>DURATION</Name>
      <TagLanguage>eng</TagLanguage>
      <DefaultLanguage>1</DefaultLanguage>
      <String>00:22:18.704000000</String>
    </Simple>
    <Simple>
      <Name>NUMBER_OF_FRAMES</Name>
      <TagLanguage>eng</TagLanguage>
      <DefaultLanguage>1</DefaultLanguage>
      <String>291</String>
    </Simple>
    <Simple>
      <Name>NUMBER_OF_BYTES</Name>
      <TagLanguage>eng</TagLanguage>
      <DefaultLanguage>1</DefaultLanguage>
      <String>12162</String>
    </Simple>
    <Simple>
      <Name>_STATISTICS_WRITING_APP</Name>
      <TagLanguage>eng</TagLanguage>
      <DefaultLanguage>1</DefaultLanguage>
      <String>mkvmerge v16.0.0 ('Protest') 32-bit</String>
    </Simple>
    <Simple>
      <Name>_STATISTICS_WRITING_DATE_UTC</Name>
      <TagLanguage>eng</TagLanguage>
      <DefaultLanguage>1</DefaultLanguage>
      <String>2018-03-04 11:43:23</String>
    </Simple>
    <Simple>
      <Name>_STATISTICS_TAGS</Name>
      <TagLanguage>eng</TagLanguage>
      <DefaultLanguage>1</DefaultLanguage>
      <String>BPS DURATION NUMBER_OF_FRAMES NUMBER_OF_BYTES</String>
    </Simple>
  </Tag>
  <Tag>
    <Targets>
      <TargetTypeValue>50</TargetTypeValue>
      <TrackUID>17907928244943436436</TrackUID>
      <TargetType>MOVIE</TargetType>
    </Targets>
    <Simple>
      <Name>BPS</Name>
      <TagLanguage>eng</TagLanguage>
      <DefaultLanguage>1</DefaultLanguage>
      <String>69</String>
    </Simple>
    <Simple>
      <Name>DURATION</Name>
      <TagLanguage>eng</TagLanguage>
      <DefaultLanguage>1</DefaultLanguage>
      <String>00:22:18.704000000</String>
    </Simple>
    <Simple>
      <Name>NUMBER_OF_FRAMES</Name>
      <TagLanguage>eng</TagLanguage>
      <DefaultLanguage>1</DefaultLanguage>
      <String>348</String>
    </Simple>
    <Simple>
      <Name>NUMBER_OF_BYTES</Name>
      <TagLanguage>eng</TagLanguage>
      <DefaultLanguage>1</DefaultLanguage>
      <String>11609</String>
    </Simple>
    <Simple>
      <Name>_STATISTICS_WRITING_APP</Name>
      <TagLanguage>eng</TagLanguage>
      <DefaultLanguage>1</DefaultLanguage>
      <String>mkvmerge v16.0.0 ('Protest') 32-bit</String>
    </Simple>
    <Simple>
      <Name>_STATISTICS_WRITING_DATE_UTC</Name>
      <TagLanguage>eng</TagLanguage>
      <DefaultLanguage>1</DefaultLanguage>
      <String>2018-03-04 11:43:23</String>
    </Simple>
    <Simple>
      <Name>_STATISTICS_TAGS</Name>
      <TagLanguage>eng</TagLanguage>
      <DefaultLanguage>1</DefaultLanguage>
      <String>BPS DURATION NUMBER_OF_FRAMES NUMBER_OF_BYTES</String>
    </Simple>
  </Tag>
  <Tag>
    <Targets>
      <TargetTypeValue>50</TargetTypeValue>
      <TrackUID>6410248588333340819</TrackUID>
      <TargetType>MOVIE</TargetType>
    </Targets>
    <Simple>
      <Name>BPS</Name>
      <TagLanguage>eng</TagLanguage>
      <DefaultLanguage>1</DefaultLanguage>
      <String>68</String>
    </Simple>
    <Simple>
      <Name>DURATION</Name>
      <TagLanguage>eng</TagLanguage>
      <DefaultLanguage>1</DefaultLanguage>
      <String>00:22:18.704000000</String>
    </Simple>
    <Simple>
      <Name>NUMBER_OF_FRAMES</Name>
      <TagLanguage>eng</TagLanguage>
      <DefaultLanguage>1</DefaultLanguage>
      <String>334</String>
    </Simple>
    <Simple>
      <Name>NUMBER_OF_BYTES</Name>
      <TagLanguage>eng</TagLanguage>
      <DefaultLanguage>1</DefaultLanguage>
      <String>11535</String>
    </Simple>
    <Simple>
      <Name>_STATISTICS_WRITING_APP</Name>
      <TagLanguage>eng</TagLanguage>
      <DefaultLanguage>1</DefaultLanguage>
      <String>mkvmerge v16.0.0 ('Protest') 32-bit</String>
    </Simple>
    <Simple>
      <Name>_STATISTICS_WRITING_DATE_UTC</Name>
      <TagLanguage>eng</TagLanguage>
      <DefaultLanguage>1</DefaultLanguage>
      <String>2018-03-04 11:43:23</String>
    </Simple>
    <Simple>
      <Name>_STATISTICS_TAGS</Name>
      <TagLanguage>eng</TagLanguage>
      <DefaultLanguage>1</DefaultLanguage>
      <String>BPS DURATION NUMBER_OF_FRAMES NUMBER_OF_BYTES</String>
    </Simple>
  </Tag>
  <Tag>
    <Targets>
      <TargetTypeValue>50</TargetTypeValue>
      <TrackUID>6815418119050881157</TrackUID>
      <TargetType>MOVIE</TargetType>
    </Targets>
    <Simple>
      <Name>BPS</Name>
      <TagLanguage>eng</TagLanguage>
      <DefaultLanguage>1</DefaultLanguage>
      <String>111</String>
    </Simple>
    <Simple>
      <Name>DURATION</Name>
      <TagLanguage>eng</TagLanguage>
      <DefaultLanguage>1</DefaultLanguage>
      <String>00:22:10.041000000</String>
    </Simple>
    <Simple>
      <Name>NUMBER_OF_FRAMES</Name>
      <TagLanguage>eng</TagLanguage>
      <DefaultLanguage>1</DefaultLanguage>
      <String>347</String>
    </Simple>
    <Simple>
      <Name>NUMBER_OF_BYTES</Name>
      <TagLanguage>eng</TagLanguage>
      <DefaultLanguage>1</DefaultLanguage>
      <String>18474</String>
    </Simple>
    <Simple>
      <Name>_STATISTICS_WRITING_APP</Name>
      <TagLanguage>eng</TagLanguage>
      <DefaultLanguage>1</DefaultLanguage>
      <String>mkvmerge v16.0.0 ('Protest') 32-bit</String>
    </Simple>
    <Simple>
      <Name>_STATISTICS_WRITING_DATE_UTC</Name>
      <TagLanguage>eng</TagLanguage>
      <DefaultLanguage>1</DefaultLanguage>
      <String>2018-03-04 11:43:23</String>
    </Simple>
    <Simple>
      <Name>_STATISTICS_TAGS</Name>
      <TagLanguage>eng</TagLanguage>
      <DefaultLanguage>1</DefaultLanguage>
      <String>BPS DURATION NUMBER_OF_FRAMES NUMBER_OF_BYTES</String>
    </Simple>
  </Tag>
  <Tag>
    <Targets>
      <TargetTypeValue>50</TargetTypeValue>
      <TrackUID>2246749809728673705</TrackUID>
      <TargetType>MOVIE</TargetType>
    </Targets>
    <Simple>
      <Name>BPS</Name>
      <TagLanguage>eng</TagLanguage>
      <DefaultLanguage>1</DefaultLanguage>
      <String>126</String>
    </Simple>
    <Simple>
      <Name>DURATION</Name>
      <TagLanguage>eng</TagLanguage>
      <DefaultLanguage>1</DefaultLanguage>
      <String>00:22:35.646000000</String>
    </Simple>
    <Simple>
      <Name>NUMBER_OF_FRAMES</Name>
      <TagLanguage>eng</TagLanguage>
      <DefaultLanguage>1</DefaultLanguage>
      <String>338</String>
    </Simple>
    <Simple>
      <Name>NUMBER_OF_BYTES</Name>
      <TagLanguage>eng</TagLanguage>
      <DefaultLanguage>1</DefaultLanguage>
      <String>21437</String>
    </Simple>
    <Simple>
      <Name>_STATISTICS_WRITING_APP</Name>
      <TagLanguage>eng</TagLanguage>
      <DefaultLanguage>1</DefaultLanguage>
      <String>mkvmerge v16.0.0 ('Protest') 32-bit</String>
    </Simple>
    <Simple>
      <Name>_STATISTICS_WRITING_DATE_UTC</Name>
      <TagLanguage>eng</TagLanguage>
      <DefaultLanguage>1</DefaultLanguage>
      <String>2018-03-04 11:43:23</String>
    </Simple>
    <Simple>
      <Name>_STATISTICS_TAGS</Name>
      <TagLanguage>eng</TagLanguage>
      <DefaultLanguage>1</DefaultLanguage>
      <String>BPS DURATION NUMBER_OF_FRAMES NUMBER_OF_BYTES</String>
    </Simple>
  </Tag>
  <Tag>
    <Targets>
      <TargetTypeValue>50</TargetTypeValue>
      <TrackUID>8958281254009330358</TrackUID>
      <TargetType>MOVIE</TargetType>
    </Targets>
    <Simple>
      <Name>BPS</Name>
      <TagLanguage>eng</TagLanguage>
      <DefaultLanguage>1</DefaultLanguage>
      <String>87</String>
    </Simple>
    <Simple>
      <Name>DURATION</Name>
      <TagLanguage>eng</TagLanguage>
      <DefaultLanguage>1</DefaultLanguage>
      <String>00:22:40.443000000</String>
    </Simple>
    <Simple>
      <Name>NUMBER_OF_FRAMES</Name>
      <TagLanguage>eng</TagLanguage>
      <DefaultLanguage>1</DefaultLanguage>
      <String>348</String>
    </Simple>
    <Simple>
      <Name>NUMBER_OF_BYTES</Name>
      <TagLanguage>eng</TagLanguage>
      <DefaultLanguage>1</DefaultLanguage>
      <String>14824</String>
    </Simple>
    <Simple>
      <Name>_STATISTICS_WRITING_APP</Name>
      <TagLanguage>eng</TagLanguage>
      <DefaultLanguage>1</DefaultLanguage>
      <String>mkvmerge v16.0.0 ('Protest') 32-bit</String>
    </Simple>
    <Simple>
      <Name>_STATISTICS_WRITING_DATE_UTC</Name>
      <TagLanguage>eng</TagLanguage>
      <DefaultLanguage>1</DefaultLanguage>
      <String>2018-03-04 11:43:23</String>
    </Simple>
    <Simple>
      <Name>_STATISTICS_TAGS</Name>
      <TagLanguage>eng</TagLanguage>
      <DefaultLanguage>1</DefaultLanguage>
      <String>BPS DURATION NUMBER_OF_FRAMES NUMBER_OF_BYTES</String>
    </Simple>
  </Tag>
  <Tag>
    <Targets>
      <TargetTypeValue>50</TargetTypeValue>
      <TrackUID>10548049183867747499</TrackUID>
      <TargetType>MOVIE</TargetType>
    </Targets>
    <Simple>
      <Name>BPS</Name>
      <TagLanguage>eng</TagLanguage>
      <DefaultLanguage>1</DefaultLanguage>
      <String>113</String>
    </Simple>
    <Simple>
      <Name>DURATION</Name>
      <TagLanguage>eng</TagLanguage>
      <DefaultLanguage>1</DefaultLanguage>
      <String>00:22:18.705000000</String>
    </Simple>
    <Simple>
      <Name>NUMBER_OF_FRAMES</Name>
      <TagLanguage>eng</TagLanguage>
      <DefaultLanguage>1</DefaultLanguage>
      <String>348</String>
    </Simple>
    <Simple>
      <Name>NUMBER_OF_BYTES</Name>
      <TagLanguage>eng</TagLanguage>
      <DefaultLanguage>1</DefaultLanguage>
      <String>18948</String>
    </Simple>
    <Simple>
      <Name>_STATISTICS_WRITING_APP</Name>
      <TagLanguage>eng</TagLanguage>
      <DefaultLanguage>1</DefaultLanguage>
      <String>mkvmerge v16.0.0 ('Protest') 32-bit</String>
    </Simple>
    <Simple>
      <Name>_STATISTICS_WRITING_DATE_UTC</Name>
      <TagLanguage>eng</TagLanguage>
      <DefaultLanguage>1</DefaultLanguage>
      <String>2018-03-04 11:43:23</String>
    </Simple>
    <Simple>
      <Name>_STATISTICS_TAGS</Name>
      <TagLanguage>eng</TagLanguage>
      <DefaultLanguage>1</DefaultLanguage>
      <String>BPS DURATION NUMBER_OF_FRAMES NUMBER_OF_BYTES</String>
    </Simple>
  </Tag>
  <Tag>
    <Targets>
      <TargetTypeValue>50</TargetTypeValue>
      <TrackUID>4198453569054100142</TrackUID>
      <TargetType>MOVIE</TargetType>
    </Targets>
    <Simple>
      <Name>BPS</Name>
      <TagLanguage>eng</TagLanguage>
      <DefaultLanguage>1</DefaultLanguage>
      <String>62</String>
    </Simple>
    <Simple>
      <Name>DURATION</Name>
      <TagLanguage>eng</TagLanguage>
      <DefaultLanguage>1</DefaultLanguage>
      <String>00:24:06.988000000</String>
    </Simple>
    <Simple>
      <Name>NUMBER_OF_FRAMES</Name>
      <TagLanguage>eng</TagLanguage>
      <DefaultLanguage>1</DefaultLanguage>
      <String>350</String>
    </Simple>
    <Simple>
      <Name>NUMBER_OF_BYTES</Name>
      <TagLanguage>eng</TagLanguage>
      <DefaultLanguage>1</DefaultLanguage>
      <String>11328</String>
    </Simple>
    <Simple>
      <Name>_STATISTICS_WRITING_APP</Name>
      <TagLanguage>eng</TagLanguage>
      <DefaultLanguage>1</DefaultLanguage>
      <String>mkvmerge v16.0.0 ('Protest') 32-bit</String>
    </Simple>
    <Simple>
      <Name>_STATISTICS_WRITING_DATE_UTC</Name>
      <TagLanguage>eng</TagLanguage>
      <DefaultLanguage>1</DefaultLanguage>
      <String>2018-03-04 11:43:23</String>
    </Simple>
    <Simple>
      <Name>_STATISTICS_TAGS</Name>
      <TagLanguage>eng</TagLanguage>
      <DefaultLanguage>1</DefaultLanguage>
      <String>BPS DURATION NUMBER_OF_FRAMES NUMBER_OF_BYTES</String>
    </Simple>
  </Tag>
  <Tag>
    <Targets>
      <TargetTypeValue>50</TargetTypeValue>
      <TrackUID>7841257390677406142</TrackUID>
      <TargetType>MOVIE</TargetType>
    </Targets>
    <Simple>
      <Name>BPS</Name>
      <TagLanguage>eng</TagLanguage>
      <DefaultLanguage>1</DefaultLanguage>
      <String>102</String>
    </Simple>
    <Simple>
      <Name>DURATION</Name>
      <TagLanguage>eng</TagLanguage>
      <DefaultLanguage>1</DefaultLanguage>
      <String>00:22:35.087000000</String>
    </Simple>
    <Simple>
      <Name>NUMBER_OF_FRAMES</Name>
      <TagLanguage>eng</TagLanguage>
      <DefaultLanguage>1</DefaultLanguage>
      <String>352</String>
    </Simple>
    <Simple>
      <Name>NUMBER_OF_BYTES</Name>
      <TagLanguage>eng</TagLanguage>
      <DefaultLanguage>1</DefaultLanguage>
      <String>17352</String>
    </Simple>
    <Simple>
      <Name>_STATISTICS_WRITING_APP</Name>
      <TagLanguage>eng</TagLanguage>
      <DefaultLanguage>1</DefaultLanguage>
      <String>mkvmerge v16.0.0 ('Protest') 32-bit</String>
    </Simple>
    <Simple>
      <Name>_STATISTICS_WRITING_DATE_UTC</Name>
      <TagLanguage>eng</TagLanguage>
      <DefaultLanguage>1</DefaultLanguage>
      <String>2018-03-04 11:43:23</String>
    </Simple>
    <Simple>
      <Name>_STATISTICS_TAGS</Name>
      <TagLanguage>eng</TagLanguage>
      <DefaultLanguage>1</DefaultLanguage>
      <String>BPS DURATION NUMBER_OF_FRAMES NUMBER_OF_BYTES</String>
    </Simple>
  </Tag>
  <Tag>
    <Targets>
      <TargetTypeValue>50</TargetTypeValue>
      <TrackUID>11570136136421164981</TrackUID>
      <TargetType>MOVIE</TargetType>
    </Targets>
    <Simple>
      <Name>BPS</Name>
      <TagLanguage>eng</TagLanguage>
      <DefaultLanguage>1</DefaultLanguage>
      <String>155</String>
    </Simple>
    <Simple>
      <Name>DURATION</Name>
      <TagLanguage>eng</TagLanguage>
      <DefaultLanguage>1</DefaultLanguage>
      <String>00:22:42.862000000</String>
    </Simple>
    <Simple>
      <Name>NUMBER_OF_FRAMES</Name>
      <TagLanguage>eng</TagLanguage>
      <DefaultLanguage>1</DefaultLanguage>
      <String>349</String>
    </Simple>
    <Simple>
      <Name>NUMBER_OF_BYTES</Name>
      <TagLanguage>eng</TagLanguage>
      <DefaultLanguage>1</DefaultLanguage>
      <String>26473</String>
    </Simple>
    <Simple>
      <Name>_STATISTICS_WRITING_APP</Name>
      <TagLanguage>eng</TagLanguage>
      <DefaultLanguage>1</DefaultLanguage>
      <String>mkvmerge v16.0.0 ('Protest') 32-bit</String>
    </Simple>
    <Simple>
      <Name>_STATISTICS_WRITING_DATE_UTC</Name>
      <TagLanguage>eng</TagLanguage>
      <DefaultLanguage>1</DefaultLanguage>
      <String>2018-03-04 11:43:23</String>
    </Simple>
    <Simple>
      <Name>_STATISTICS_TAGS</Name>
      <TagLanguage>eng</TagLanguage>
      <DefaultLanguage>1</DefaultLanguage>
      <String>BPS DURATION NUMBER_OF_FRAMES NUMBER_OF_BYTES</String>
    </Simple>
  </Tag>
  <Tag>
    <Targets>
      <TargetTypeValue>50</TargetTypeValue>
      <TrackUID>4357521441054651538</TrackUID>
      <TargetType>MOVIE</TargetType>
    </Targets>
    <Simple>
      <Name>BPS</Name>
      <TagLanguage>eng</TagLanguage>
      <DefaultLanguage>1</DefaultLanguage>
      <String>80</String>
    </Simple>
    <Simple>
      <Name>DURATION</Name>
      <TagLanguage>eng</TagLanguage>
      <DefaultLanguage>1</DefaultLanguage>
      <String>00:22:18.838000000</String>
    </Simple>
    <Simple>
      <Name>NUMBER_OF_FRAMES</Name>
      <TagLanguage>eng</TagLanguage>
      <DefaultLanguage>1</DefaultLanguage>
      <String>358</String>
    </Simple>
    <Simple>
      <Name>NUMBER_OF_BYTES</Name>
      <TagLanguage>eng</TagLanguage>
      <DefaultLanguage>1</DefaultLanguage>
      <String>13408</String>
    </Simple>
    <Simple>
      <Name>_STATISTICS_WRITING_APP</Name>
      <TagLanguage>eng</TagLanguage>
      <DefaultLanguage>1</DefaultLanguage>
      <String>mkvmerge v16.0.0 ('Protest') 32-bit</String>
    </Simple>
    <Simple>
      <Name>_STATISTICS_WRITING_DATE_UTC</Name>
      <TagLanguage>eng</TagLanguage>
      <DefaultLanguage>1</DefaultLanguage>
      <String>2018-03-04 11:43:23</String>
    </Simple>
    <Simple>
      <Name>_STATISTICS_TAGS</Name>
      <TagLanguage>eng</TagLanguage>
      <DefaultLanguage>1</DefaultLanguage>
      <String>BPS DURATION NUMBER_OF_FRAMES NUMBER_OF_BYTES</String>
    </Simple>
  </Tag>
  <Tag>
    <Targets>
      <TargetTypeValue>50</TargetTypeValue>
      <TrackUID>6128751924542150588</TrackUID>
      <TargetType>MOVIE</TargetType>
    </Targets>
    <Simple>
      <Name>BPS</Name>
      <TagLanguage>eng</TagLanguage>
      <DefaultLanguage>1</DefaultLanguage>
      <String>67</String>
    </Simple>
    <Simple>
      <Name>DURATION</Name>
      <TagLanguage>eng</TagLanguage>
      <DefaultLanguage>1</DefaultLanguage>
      <String>00:22:19.005000000</String>
    </Simple>
    <Simple>
      <Name>NUMBER_OF_FRAMES</Name>
      <TagLanguage>eng</TagLanguage>
      <DefaultLanguage>1</DefaultLanguage>
      <String>356</String>
    </Simple>
    <Simple>
      <Name>NUMBER_OF_BYTES</Name>
      <TagLanguage>eng</TagLanguage>
      <DefaultLanguage>1</DefaultLanguage>
      <String>11241</String>
    </Simple>
    <Simple>
      <Name>_STATISTICS_WRITING_APP</Name>
      <TagLanguage>eng</TagLanguage>
      <DefaultLanguage>1</DefaultLanguage>
      <String>mkvmerge v16.0.0 ('Protest') 32-bit</String>
    </Simple>
    <Simple>
      <Name>_STATISTICS_WRITING_DATE_UTC</Name>
      <TagLanguage>eng</TagLanguage>
      <DefaultLanguage>1</DefaultLanguage>
      <String>2018-03-04 11:43:23</String>
    </Simple>
    <Simple>
      <Name>_STATISTICS_TAGS</Name>
      <TagLanguage>eng</TagLanguage>
      <DefaultLanguage>1</DefaultLanguage>
      <String>BPS DURATION NUMBER_OF_FRAMES NUMBER_OF_BYTES</String>
    </Simple>
  </Tag>
  <Tag>
    <Targets>
      <TargetTypeValue>50</TargetTypeValue>
      <TrackUID>8387016866832575139</TrackUID>
      <TargetType>MOVIE</TargetType>
    </Targets>
    <Simple>
      <Name>BPS</Name>
      <TagLanguage>eng</TagLanguage>
      <DefaultLanguage>1</DefaultLanguage>
      <String>67</String>
    </Simple>
    <Simple>
      <Name>DURATION</Name>
      <TagLanguage>eng</TagLanguage>
      <DefaultLanguage>1</DefaultLanguage>
      <String>00:22:19.005000000</String>
    </Simple>
    <Simple>
      <Name>NUMBER_OF_FRAMES</Name>
      <TagLanguage>eng</TagLanguage>
      <DefaultLanguage>1</DefaultLanguage>
      <String>354</String>
    </Simple>
    <Simple>
      <Name>NUMBER_OF_BYTES</Name>
      <TagLanguage>eng</TagLanguage>
      <DefaultLanguage>1</DefaultLanguage>
      <String>11372</String>
    </Simple>
    <Simple>
      <Name>_STATISTICS_WRITING_APP</Name>
      <TagLanguage>eng</TagLanguage>
      <DefaultLanguage>1</DefaultLanguage>
      <String>mkvmerge v16.0.0 ('Protest') 32-bit</String>
    </Simple>
    <Simple>
      <Name>_STATISTICS_WRITING_DATE_UTC</Name>
      <TagLanguage>eng</TagLanguage>
      <DefaultLanguage>1</DefaultLanguage>
      <String>2018-03-04 11:43:23</String>
    </Simple>
    <Simple>
      <Name>_STATISTICS_TAGS</Name>
      <TagLanguage>eng</TagLanguage>
      <DefaultLanguage>1</DefaultLanguage>
      <String>BPS DURATION NUMBER_OF_FRAMES NUMBER_OF_BYTES</String>
    </Simple>
  </Tag>
  <Tag>
    <Targets>
      <TargetTypeValue>50</TargetTypeValue>
      <TrackUID>7494719363741144251</TrackUID>
      <TargetType>MOVIE</TargetType>
    </Targets>
    <Simple>
      <Name>BPS</Name>
      <TagLanguage>eng</TagLanguage>
      <DefaultLanguage>1</DefaultLanguage>
      <String>103</String>
    </Simple>
    <Simple>
      <Name>DURATION</Name>
      <TagLanguage>eng</TagLanguage>
      <DefaultLanguage>1</DefaultLanguage>
      <String>00:23:49.028000000</String>
    </Simple>
    <Simple>
      <Name>NUMBER_OF_FRAMES</Name>
      <TagLanguage>eng</TagLanguage>
      <DefaultLanguage>1</DefaultLanguage>
      <String>391</String>
    </Simple>
    <Simple>
      <Name>NUMBER_OF_BYTES</Name>
      <TagLanguage>eng</TagLanguage>
      <DefaultLanguage>1</DefaultLanguage>
      <String>18481</String>
    </Simple>
    <Simple>
      <Name>_STATISTICS_WRITING_APP</Name>
      <TagLanguage>eng</TagLanguage>
      <DefaultLanguage>1</DefaultLanguage>
      <String>mkvmerge v16.0.0 ('Protest') 32-bit</String>
    </Simple>
    <Simple>
      <Name>_STATISTICS_WRITING_DATE_UTC</Name>
      <TagLanguage>eng</TagLanguage>
      <DefaultLanguage>1</DefaultLanguage>
      <String>2018-03-04 11:43:23</String>
    </Simple>
    <Simple>
      <Name>_STATISTICS_TAGS</Name>
      <TagLanguage>eng</TagLanguage>
      <DefaultLanguage>1</DefaultLanguage>
      <String>BPS DURATION NUMBER_OF_FRAMES NUMBER_OF_BYTES</String>
    </Simple>
  </Tag>
</Tags>
