<?xml version="1.0"?>
<!-- <!DOCTYPE Chapters SYSTEM "matroskachapters.dtd"> -->
<Chapters>
  <EditionEntry>
    <EditionUID>8518596033396227752</EditionUID>
    <ChapterAtom>
      <ChapterUID>8840184603551884276</ChapterUID>
      <ChapterTimeStart>00:00:00.000000000</ChapterTimeStart>
      <ChapterDisplay>
        <ChapterString>Intro</ChapterString>
        <ChapterLanguage>eng</ChapterLanguage>
      </ChapterDisplay>
    </ChapterAtom>
    <ChapterAtom>
      <ChapterUID>4065400257144562715</ChapterUID>
      <ChapterDisplay>
        <ChapterString>OP</ChapterString>
        <ChapterLanguage>eng</ChapterLanguage>
      </ChapterDisplay>
      <ChapterTimeStart>00:00:57.057000000</ChapterTimeStart>
    </ChapterAtom>
    <ChapterAtom>
      <ChapterUID>2083919962079224791</ChapterUID>
      <ChapterDisplay>
        <ChapterString>Part A</ChapterString>
        <ChapterLanguage>eng</ChapterLanguage>
      </ChapterDisplay>
      <ChapterTimeStart>00:02:27.022000000</ChapterTimeStart>
    </ChapterAtom>
    <ChapterAtom>
      <ChapterUID>11897115203672375527</ChapterUID>
      <ChapterDisplay>
        <ChapterString>Part B</ChapterString>
        <ChapterLanguage>eng</ChapterLanguage>
      </ChapterDisplay>
      <ChapterTimeStart>00:12:07.018000000</ChapterTimeStart>
    </ChapterAtom>
    <ChapterAtom>
      <ChapterUID>609910944748232334</ChapterUID>
      <ChapterDisplay>
        <ChapterString>ED</ChapterString>
        <ChapterLanguage>eng</ChapterLanguage>
      </ChapterDisplay>
      <ChapterTimeStart>00:21:09.810000000</ChapterTimeStart>
    </ChapterAtom>
    <ChapterAtom>
      <ChapterUID>16773034920216229893</ChapterUID>
      <ChapterDisplay>
        <ChapterString>Preview</ChapterString>
        <ChapterLanguage>eng</ChapterLanguage>
      </ChapterDisplay>
      <ChapterTimeStart>00:23:35.039000000</ChapterTimeStart>
    </ChapterAtom>
  </EditionEntry>
</Chapters>
